sqlframe_gizmosql/__init__.py
sqlframe_gizmosql/activate.py
sqlframe_gizmosql/catalog.py
sqlframe_gizmosql/column.py
sqlframe_gizmosql/connect.py
sqlframe_gizmosql/dataframe.py
sqlframe_gizmosql/functions.py
sqlframe_gizmosql/functions.pyi
sqlframe_gizmosql/group.py
sqlframe_gizmosql/readwriter.py
sqlframe_gizmosql/session.py
sqlframe_gizmosql/table.py
sqlframe_gizmosql/types.py
sqlframe_gizmosql/udf.py
sqlframe_gizmosql/window.py
sqlframe_gizmosql-0.1.2.dist-info/METADATA
sqlframe_gizmosql-0.1.2.dist-info/WHEEL
sqlframe_gizmosql-0.1.2.dist-info/RECORD
