Metadata-Version: 2.4
Name: sqlframe-gizmosql
Version: 0.1.2
Summary: GizmoSQL adapter for SQLFrame - PySpark-like DataFrame API for GizmoSQL
Project-URL: Homepage, https://github.com/gizmodata/sqlframe-gizmosql
Project-URL: Repository, https://github.com/gizmodata/sqlframe-gizmosql
Project-URL: Issues, https://github.com/gizmodata/sqlframe-gizmosql/issues
Author-email: Philip Moore <philip@gizmodata.com>
License-Expression: Apache-2.0
Keywords: arrow,dataframe,duckdb,flight-sql,gizmosql,pyspark,sql,sqlframe
Classifier: Development Status :: 4 - Beta
Classifier: Intended Audience :: Developers
Classifier: License :: OSI Approved :: Apache Software License
Classifier: Operating System :: OS Independent
Classifier: Programming Language :: Python :: 3
Classifier: Programming Language :: Python :: 3.10
Classifier: Programming Language :: Python :: 3.11
Classifier: Programming Language :: Python :: 3.12
Classifier: Programming Language :: Python :: 3.13
Classifier: Programming Language :: Python :: 3.14
Classifier: Topic :: Database
Classifier: Topic :: Software Development :: Libraries :: Python Modules
Requires-Python: >=3.10
Requires-Dist: adbc-driver-flightsql>=1.10.0
Requires-Dist: pyarrow>=23.0.0
Requires-Dist: sqlframe>=3.0.0
Provides-Extra: dev
Requires-Dist: pytest-cov>=4.0.0; extra == 'dev'
Requires-Dist: pytest>=7.0.0; extra == 'dev'
Requires-Dist: ruff>=0.4.0; extra == 'dev'
